{
    "criteria": {
      "requirement": {
        "trigger": "minecraft:item_used_on_block",
        "conditions": {
          "item": {
            "items": [
              "minecraft:command_block"
            ],
            "nbt": "{dusk_id:\"soul\"}"
          },
          "location": {
            "block": {
              "blocks": [
                "minecraft:campfire"
              ]
            }
          }
        }
      }
    },
    "rewards": {
      "function": "dusk:adv/use_altar"
    }
  }
  